.VERSION
AUTHORS.rst
CONTRIBUTING.rst
HISTORY.rst
LICENSE
MANIFEST.in
Pipfile
Pipfile.lock
README.rst
USAGE.rst
dev-requirements.txt
requirements.txt
setup.cfg
setup.py
docs/Makefile
docs/authors.rst
docs/conf.py
docs/contributing.rst
docs/history.rst
docs/index.rst
docs/installation.rst
docs/readme.rst
docs/usage.rst
tests/test_wikiseriesbaslib.py
wikiseriesbaslib/.VERSION
wikiseriesbaslib/AUTHORS.rst
wikiseriesbaslib/CONTRIBUTING.rst
wikiseriesbaslib/HISTORY.rst
wikiseriesbaslib/LICENSE
wikiseriesbaslib/Pipfile
wikiseriesbaslib/Pipfile.lock
wikiseriesbaslib/README.rst
wikiseriesbaslib/USAGE.rst
wikiseriesbaslib/__init__.py
wikiseriesbaslib/_version.py
wikiseriesbaslib/dev-requirements.txt
wikiseriesbaslib/requirements.txt
wikiseriesbaslib/wikiseriesbaslib.py
wikiseriesbaslib/wikiseriesbaslibexceptions.py
wikiseriesbaslib.egg-info/PKG-INFO
wikiseriesbaslib.egg-info/SOURCES.txt
wikiseriesbaslib.egg-info/dependency_links.txt
wikiseriesbaslib.egg-info/not-zip-safe
wikiseriesbaslib.egg-info/requires.txt
wikiseriesbaslib.egg-info/top_level.txt