Metadata-Version: 2.1
Name: wikiseriesbaslib
Version: 0.1.0
Summary: Library to use wikipedia to query tv series episode list
Home-page: https://github.com/bvk007/wikiseriesbaslib
Author: Bas van Kesteren
Author-email: bvkdummy@gmail.com
License: MIT
Keywords: wikiseriesbaslib wikipedia tv series
Classifier: Development Status :: 3 - Alpha
Classifier: Intended Audience :: Developers
Classifier: License :: OSI Approved :: MIT License
Classifier: Natural Language :: English
Classifier: Programming Language :: Python :: 3.9
License-File: LICENSE
License-File: AUTHORS.rst
